ozonapi/__init__.py
ozonapi/infrastructure/logging/__init__.py
ozonapi/infrastructure/logging/config.py
ozonapi/infrastructure/logging/factory.py
ozonapi/infrastructure/logging/manager.py
ozonapi/infrastructure/logging/formatters/__init__.py
ozonapi/infrastructure/logging/formatters/base.py
ozonapi/infrastructure/logging/handlers/__init__.py
ozonapi/infrastructure/logging/handlers/base.py
ozonapi/seller/__init__.py
ozonapi/seller/common/__init__.py
ozonapi/seller/common/enumerations/__init__.py
ozonapi/seller/common/enumerations/company.py
ozonapi/seller/common/enumerations/delivery.py
ozonapi/seller/common/enumerations/localization.py
ozonapi/seller/common/enumerations/postings.py
ozonapi/seller/common/enumerations/prices.py
ozonapi/seller/common/enumerations/products.py
ozonapi/seller/common/enumerations/requests.py
ozonapi/seller/common/enumerations/warehouses.py
ozonapi/seller/core/__init__.py
ozonapi/seller/core/config.py
ozonapi/seller/core/core.py
ozonapi/seller/core/exceptions.py
ozonapi/seller/core/method_rate_limiter.py
ozonapi/seller/core/rate_limiter.py
ozonapi/seller/core/sessions.py
ozonapi/seller/methods/__init__.py
ozonapi/seller/methods/attributes_and_characteristics/__init__.py
ozonapi/seller/methods/attributes_and_characteristics/description_category_attribute.py
ozonapi/seller/methods/attributes_and_characteristics/description_category_attribute_values.py
ozonapi/seller/methods/attributes_and_characteristics/description_category_attribute_values_search.py
ozonapi/seller/methods/attributes_and_characteristics/description_category_tree.py
ozonapi/seller/methods/barcodes/__init__.py
ozonapi/seller/methods/barcodes/barcode_add.py
ozonapi/seller/methods/barcodes/barcode_generate.py
ozonapi/seller/methods/beta/__init__.py
ozonapi/seller/methods/beta/analytics_stocks.py
ozonapi/seller/methods/beta/seller_info.py
ozonapi/seller/methods/fbo/__init__.py
ozonapi/seller/methods/fbo/posting_fbo_cancel_reason_list.py
ozonapi_async-0.19.3.dist-info/licenses/LICENSE
ozonapi_async-0.19.3.dist-info/METADATA
ozonapi_async-0.19.3.dist-info/WHEEL
ozonapi_async-0.19.3.dist-info/top_level.txt
ozonapi_async-0.19.3.dist-info/RECORD
