Metadata-Version: 2.4
Name: ozonapi-async
Version: 0.19.3
Summary: Асинхронный pydantic-интерфейс для Ozon Seller API c ограничением запросов и docstrings
Author-email: Alexander Ulianov <a.v.ulianov@mail.ru>
License: MIT
Project-URL: Homepage, https://github.com/a-ulianov/OzonAPI
Project-URL: Documentation, https://github.com/a-ulianov/OzonAPI#readme
Project-URL: Repository, https://github.com/a-ulianov/OzonAPI
Project-URL: Issues, https://github.com/a-ulianov/OzonAPI/issues
Project-URL: Changelog, https://github.com/a-ulianov/OzonAPI/releases
Keywords: ozon,api,async,ecommerce,seller,docstring,pydantic,analytics,prices,stocks,oauth,python
Classifier: Development Status :: 4 - Beta
Classifier: Intended Audience :: Developers
Classifier: License :: OSI Approved :: MIT License
Classifier: Operating System :: OS Independent
Classifier: Programming Language :: Python :: 3
Classifier: Programming Language :: Python :: 3.9
Classifier: Programming Language :: Python :: 3.10
Classifier: Programming Language :: Python :: 3.11
Classifier: Programming Language :: Python :: 3.12
Classifier: Programming Language :: Python :: 3.13
Classifier: Topic :: Software Development :: Libraries :: Python Modules
Requires-Python: <4.0,>=3.9
License-File: LICENSE
Requires-Dist: aiohttp<4.0.0,>=3.13.1
Requires-Dist: tenacity<10.0.0,>=9.1.2
Requires-Dist: aiolimiter<2.0.0,>=1.2.1
Requires-Dist: pydantic<3.0.0,>=2.12.3
Requires-Dist: pydantic-settings<3.0.0,>=2.11.0
Requires-Dist: async-lru<3.0.0,>=2.0.5
Provides-Extra: test
Requires-Dist: pytest<9.0.0,>=8.4.2; extra == "test"
Requires-Dist: pytest-cov<8.0.0,>=7.0.0; extra == "test"
Requires-Dist: pytest-asyncio<2.0.0,>=1.2.0; extra == "test"
Provides-Extra: dev
Requires-Dist: pytest<9.0.0,>=8.4.2; extra == "dev"
Requires-Dist: pytest-cov<8.0.0,>=7.0.0; extra == "dev"
Requires-Dist: pytest-asyncio<2.0.0,>=1.2.0; extra == "dev"
Dynamic: license-file
